csv_helpers/__init__.py
csv_helpers/csv_general_helpers.py
csv_helpers/csv_reading_helpers.py
csv_helpers/csv_writing_helpers.py
csv_helpers/tests/__init__.py
csv_helpers/tests/test_csv_general_helpers.py
csv_helpers/tests/test_csv_reading_helpers.py
csv_helpers/tests/test_csv_writing_helpers.py
ctodd_python_lib_csv-1.0.2.dist-info/LICENSE.txt
ctodd_python_lib_csv-1.0.2.dist-info/METADATA
ctodd_python_lib_csv-1.0.2.dist-info/RECORD
ctodd_python_lib_csv-1.0.2.dist-info/WHEEL
ctodd_python_lib_csv-1.0.2.dist-info/top_level.txt
